tutorowly/__about__.py
tutorowly/__init__.py
tutorowly/plugin.py
tutorowly/patches/.gitignore
tutorowly/patches/mfe-dockerfile-post-npm-install
tutorowly/patches/openedx-dockerfile-post-python-requirements
tutorowly/templates/owly/apps/.gitignore
tutorowly/templates/owly/build/.gitignore
tutorowly/templates/owly/tasks/owly/.gitignore
tutor_contrib_owly-19.6.1.dist-info/METADATA
tutor_contrib_owly-19.6.1.dist-info/WHEEL
tutor_contrib_owly-19.6.1.dist-info/entry_points.txt
tutor_contrib_owly-19.6.1.dist-info/RECORD
