Metadata-Version: 2.4
Name: tutor-contrib-owly
Version: 19.6.1
Summary: Bring the power of AI to Open edX with Owly!
Project-URL: Documentation, https://github.com/aulasneo/tutor-contrib-owly#readme
Project-URL: Issues, https://github.com/aulasneo/tutor-contrib-owly/issues
Project-URL: Source, https://github.com/aulasneo/tutor-contrib-owly
Author: Andres Gonzalez
Author-email: andres@aulasneo.com
License: Proprietary
Classifier: Development Status :: 3 - Alpha
Classifier: Intended Audience :: Developers
Classifier: License :: Other/Proprietary License
Classifier: Operating System :: OS Independent
Classifier: Programming Language :: Python
Classifier: Programming Language :: Python :: 3.9
Classifier: Programming Language :: Python :: 3.10
Classifier: Programming Language :: Python :: 3.11
Classifier: Programming Language :: Python :: 3.12
Classifier: Programming Language :: Python :: Implementation :: CPython
Classifier: Programming Language :: Python :: Implementation :: PyPy
Requires-Python: >=3.9
Requires-Dist: tutor<20.0.0,>=19.0.0
Provides-Extra: dev
Requires-Dist: tutor[dev]<20.0.0,>=19.0.0; extra == 'dev'
